ARCHVM/labwork2/stack_structural.sv

module stack_structural_lite(
    output wire[3:0] O_DATA, 
    input wire RESET, 
    input wire CLK, 
    input wire[1:0] COMMAND, 
    input wire[2:0] INDEX,
    input wire[3:0] I_DATA
    );
    wire[3:0] command;
    wire[2:0] current_cell_out;
    wire[2:0] current_cell_in;
    wire[2:0] push_out;
    wire[2:0] pop_out;
    wire[2:0] cmd0_out;
    wire[2:0] get_out;
    wire[3:0] pop_O_DATA;
    wire[3:0] get_O_DATA;
    wire[3:0] new_pop_O_DATA;
    wire[3:0] new_get_O_DATA;
    wire[7:0] s;
    wire[3:0] wire_memory_cell [7:0];
    wire[3:0] cell_[7:0];

    demultiplexer4 mult4(command, COMMAND);

    not (n_reset, RESET);

    or (new_CLK, CLK, RESET);

    or3 or_3(current_cell_in,  push_out, pop_out, cmd0_out, get_out);

    and14 pop_O_data(new_pop_O_DATA, new_CLK, pop_O_DATA);

    and14 get_o_data(new_get_O_DATA, new_CLK, get_O_DATA);

    or4_2wire or4_2(O_DATA, new_pop_O_DATA, new_get_O_DATA);
    
    always @(CLK) begin
        //$display(command[2], " ", current_cell_out, " ", pop_out, " ", cell_[0], " ", cell_[1], " ", cell_[2], " ", cell_[3], " ", cell_[4], " ", cell_[5], " ", cell_[6], " ", cell_[7]);
        //$display(CLK, " ", push_out, " ",  current_cell_out, " ", current_cell_in, " ", command[1]);
        //$display(CLK, " ", RESET, " ", current_cell_out, " ", cell_[0], " ", cell_[1], " ", cell_[2], " ", cell_[3], " ", cell_[4], " ", cell_[5], " ", cell_[6], " ", cell_[7]);
    end

    current_cell curr_cell(current_cell_out, current_cell_in, new_CLK, RESET);

    push push_(push_out, wire_memory_cell, s, command[1], I_DATA, current_cell_out);

    pop pop_(pop_out, pop_O_DATA, cell_, command[2], current_cell_out);

    command_00 cmd0(cmd0_out, current_cell_out, command[0]);

    get get_(get_out, get_O_DATA, INDEX, cell_, command[3], current_cell_out);

    wire[3:0] d0;
    wire[3:0] d1;
    wire[3:0] d2;
    wire[3:0] d3;
    wire[3:0] d4;
    wire[3:0] d5;
    wire[3:0] d6;
    wire[3:0] d7;

    and14 and_d0(d0, n_reset, wire_memory_cell[0]);
    and14 and_d1(d1, n_reset, wire_memory_cell[1]);
    and14 and_d2(d2, n_reset, wire_memory_cell[2]);
    and14 and_d3(d3, n_reset, wire_memory_cell[3]);
    and14 and_d4(d4, n_reset, wire_memory_cell[4]);
    and14 and_d5(d5, n_reset, wire_memory_cell[5]);
    and14 and_d6(d6, n_reset, wire_memory_cell[6]);
    and14 and_d7(d7, n_reset, wire_memory_cell[7]);

    or (s0, s[0], RESET);
    or (s1, s[1], RESET);
    or (s2, s[2], RESET);
    or (s3, s[3], RESET);
    or (s4, s[4], RESET);
    or (s5, s[5], RESET);
    or (s6, s[6], RESET);
    or (s7, s[7], RESET);

    memory_cell cell1(cell_[0], d0, new_CLK, s0);
    memory_cell cell2(cell_[1], d1, new_CLK, s1);
    memory_cell cell3(cell_[2], d2, new_CLK, s2);
    memory_cell cell4(cell_[3], d3, new_CLK, s3);
    memory_cell cell5(cell_[4], d4, new_CLK, s4);
    memory_cell cell6(cell_[5], d5, new_CLK, s5);
    memory_cell cell7(cell_[6], d6, new_CLK, s6);
    memory_cell cell8(cell_[7], d7, new_CLK, s7);



    // always @(*) begin
    //     $display(CLK, " ",COMMAND, " ", command[0], " ", command[1], " ", command[2], " ", command[3]);
    // end

    // reg[3:0] out_data;
    // wire[2:0] current_cell_out;
    // wire[2:0] current_cell_in;
    // wire[3:0] command;
    // wire[2:0] push_out;
    // wire[2:0] pop_out;


    // always begin
    //     #1; $display("%3b %2b %3b %3b", current_cell_out, pop_out, push_out, current_cell_in);
    // end
    //     //#4; $display("%5b\t%5b\t%5b\t%5b\t%5b\t%5b\t%5b\t%5b\t", cell_[0], cell_[1], cell_[2], cell_[3], cell_[4], cell_[5], cell_[6], cell_[7]);

    // put your code here, the other module MUST be deleted
    // don't edit module interface

endmodule

module or4_2wire(output wire[3:0] o_data, input wire[3:0] input_1, input_2);
    or (o_data[0], input_1[0], input_2[0]);
    or (o_data[1], input_1[1], input_2[1]);
    or (o_data[2], input_1[2], input_2[2]);
    or (o_data[3], input_1[3], input_2[3]);
endmodule

module command_00(output wire[2:0] data_o, input wire[2:0] data_i, input c0);
    and13 and1_3(data_o, c0, data_i);
endmodule

module or3(output wire[2:0] data_o, input wire[2:0] input_1, input_2, input_3, input_4);
    or (data_o[0], input_1[0], input_2[0], input_3[0], input_4[0]);
    or (data_o[1], input_1[1], input_2[1], input_3[1], input_4[1]);
    or (data_o[2], input_1[2], input_2[2], input_3[2], input_4[2]);
endmodule


module or4(output wire[3:0] data_o, input wire[3:0] input_1, input_2, input_3, input_4, input_5, input_6, input_7, input_8);
    or (data_o[0], input_1[0], input_2[0], input_3[0], input_4[0], input_5[0], input_6[0], input_7[0], input_8[0]);
    or (data_o[1], input_1[1], input_2[1], input_3[1], input_4[1], input_5[1], input_6[1], input_7[1], input_8[1]);
    or (data_o[2], input_1[2], input_2[2], input_3[2], input_4[2], input_5[2], input_6[2], input_7[2], input_8[2]);
    or (data_o[3], input_3[3], input_2[3], input_3[3], input_4[3], input_5[3], input_6[3], input_7[3], input_8[3]);
endmodule

module demultiplexer4(output wire[3:0] o, input wire[1:0] data_i);
    not (n_d0, data_i[0]);
    not (n_d1, data_i[1]);


    and (o[0], n_d0, n_d1);
    and (o[1], data_i[0], n_d1);
    and (o[2], n_d0, data_i[1]);
    and (o[3], data_i[0], data_i[1]);
endmodule

module rs_trigger(output wire q, n_q, input wire r, s, clk);
    and (and_r, clk, r);
    and (and_s, clk, s);
    wire nor_r, nor_s;
    nor (nor_r, and_r, nor_s);
    nor (nor_s, and_s, nor_r);
    assign q = nor_r;
    assign n_q = nor_s;
endmodule


module d_trigger(output q, input d, clk, reset);
    not (n_clk, clk);
    not (n_reset, reset);

    or (new_clk, clk, reset);
    or (new_n_clk, n_clk, reset);

    and (new_d, d, n_reset);
    not (n_d, new_d);

    rs_trigger rs_1(rs_1_q, rs_1_nq, n_d, new_d, new_clk);

    and (new_rs_1_q, rs_1_q, n_reset);
    or (new_rs_1_nq, rs_1_nq, reset);

    rs_trigger rs_2(q, rs_2_nq, new_rs_1_nq, new_rs_1_q, new_n_clk);
endmodule


module current_cell(output wire[2:0] data_o, input wire[2:0] data_i, input wire clk, reset);
    d_trigger d_1(data_o[0], data_i[0], clk, reset);
    d_trigger d_2(data_o[1], data_i[1], clk, reset);
    d_trigger d_3(data_o[2], data_i[2], clk, reset);
endmodule

module memory_cell(output wire[3:0] data_o, input wire[3:0] input_data, input wire clk, input wire state);
    wire tmp;
    rs_trigger bit1(data_o[0], tmp, ((~input_data[0]) & state), (input_data[0] & state), clk);
    rs_trigger bit2(data_o[1], tmp, ((~input_data[1]) & state), (input_data[1] & state), clk);
    rs_trigger bit3(data_o[2], tmp, ((~input_data[2]) & state), (input_data[2] & state), clk);
    rs_trigger bit4(data_o[3], tmp, ((~input_data[3]) & state), (input_data[3] & state), clk);
endmodule

module half_summer(output r, c, input a, b);
    and (and_a_b, a, b);
    xor (xor_a_b, a, b);
    assign r = xor_a_b;
    assign c = and_a_b;
endmodule

module summer_1_3(output wire[2:0] data_o, input wire a, input wire[2:0] b);
    half_summer sum0(data_o[0], carry_0, a, b[0]);
    half_summer sum1(data_o[1], carry_1, carry_0, b[1]);
    half_summer sum2(data_o[2], carry_2, carry_1, b[2]);
endmodule

module demultiplexer8(output wire[7:0] o, input wire[2:0] data_i);
    not (n_d0, data_i[0]);
    not (n_d1, data_i[1]);
    not (n_d2, data_i[2]);

    and (o[0], n_d0, n_d1, n_d2);
    and (o[1], data_i[0], n_d1, n_d2);
    and (o[2], n_d0, data_i[1], n_d2);
    and (o[3], data_i[0], data_i[1], n_d2);
    and (o[4], n_d0, n_d1, data_i[2]);
    and (o[5], data_i[0], n_d1, data_i[2]);
    and (o[6], n_d0, data_i[1], data_i[2]);
    and (o[7], data_i[0], data_i[1], data_i[2]);
endmodule

module and13(output wire[2:0] data_o, input d1, input wire[2:0] d3);
    and (data_o[0], d1, d3[0]);
    and (data_o[1], d1, d3[1]);
    and (data_o[2], d1, d3[2]);
endmodule


module and14(output wire[3:0] data_o, input d1, input wire[3:0] d4);
    and (data_o[0], d1, d4[0]);
    and (data_o[1], d1, d4[1]);
    and (data_o[2], d1, d4[2]);
    and (data_o[3], d1, d4[3]);
endmodule

module push(output wire[2:0] push_o, 
    output wire[3:0] d [7:0],
    output wire[7:0] s,

    input wire c1, 
    input wire[3:0] data_i,
    input wire[2:0] current_cell_
    );
    wire[7:0] o;
    wire[2:0] result_sum;

    summer_1_3 sum(result_sum, c1, current_cell_);

    and13 and_1_3(push_o, c1, result_sum);

    demultiplexer8 mult(o, result_sum);

    and14 d0(d[0], o[0], data_i);
    and (s[0], c1, o[0]);

    and14 d1(d[1], o[1], data_i);
    and (s[1], c1, o[1]);

    and14 d2(d[2], o[2], data_i);
    and (s[2], c1, o[2]);

    and14 d3(d[3], o[3], data_i);
    and (s[3], c1, o[3]);

    and14 d4(d[4], o[4], data_i);
    and (s[4], c1, o[4]);

    and14 d5(d[5], o[5], data_i);
    and (s[5], c1, o[5]);

    and14 d6(d[6], o[6], data_i);
    and (s[6], c1, o[6]);

    and14 d7(d[7], o[7], data_i);
    and (s[7], c1, o[7]);
endmodule

module half_substractor(output diff, bor, input a, b);
    xor (diff, a, b);

    not (n_a, a);
    and (bor, n_a, b);
endmodule

module substractor_3_1(output wire[2:0] data_o, input wire[2:0] data_i, input d);
    half_substractor h_sub1(data_o[0], bor1, data_i[0], d);
    half_substractor h_sub2(data_o[1], bor2, data_i[1], bor1);
    half_substractor h_sub3(data_o[2], bor3, data_i[2], bor2);
endmodule

module pop(output wire[2:0] pop_out,
    output wire[3:0] o_data,

    input wire[3:0] d [7:0],
    input wire c2, 
    input wire[2:0] current_cell_
    );
    wire[2:0] tmp_out;
    substractor_3_1 sub_3_1(tmp_out, current_cell_, c2);

    and13 and_13(pop_out, c2, tmp_out);

    wire[7:0] o;

    demultiplexer8 mult(o, current_cell_);

    wire[3:0] d_0;
    wire[3:0] d_1;
    wire[3:0] d_2;
    wire[3:0] d_3;
    wire[3:0] d_4;
    wire[3:0] d_5;
    wire[3:0] d_6;
    wire[3:0] d_7;

    and14 d0(d_0, o[0], d[0]);
    and14 d1(d_1, o[1], d[1]);
    and14 d2(d_2, o[2], d[2]);
    and14 d3(d_3, o[3], d[3]);
    and14 d4(d_4, o[4], d[4]);
    and14 d5(d_5, o[5], d[5]);
    and14 d6(d_6, o[6], d[6]);
    and14 d7(d_7, o[7], d[7]);

    wire[3:0] tmp_data;

    or4 or_4(tmp_data, d_0, d_1, d_2, d_3, d_4, d_5, d_6, d_7);

    and14 and_14(o_data, c2, tmp_data);
endmodule

module substractor(output d, bout, input a, b, bin);
    half_substractor hs1(hs1_diff, bor_1, a, b);
    half_substractor hs2(d, bor_2, hs1_diff, bin);

    or (bout, bor_1, bor_2);
endmodule

module substractor_3_3(output wire[2:0] data_o, input wire[2:0] input1, input2);
    half_substractor hs1(data_o[0], bor0, input1[0], input2[0]);
    substractor s2(data_o[1], bor1, input1[1], input2[1], bor0);
    substractor s3(data_o[2], bor2, input1[2], input2[2], bor1);
endmodule

module get(output wire[2:0] get_out, 
    output wire[3:0] o_data,

    input wire[2:0] index,
    input wire[3:0] d [7:0],
    input wire c3,
    input wire[2:0] current_cell_
    );

    and13 and1_3(get_out, c3, current_cell_);

    wire[2:0] tmp_out;

    substractor_3_3 sub_3_3(tmp_out, current_cell_, index);

    wire[7:0] o;

    demultiplexer8 mult(o, tmp_out);

    wire[3:0] d_0;
    wire[3:0] d_1;
    wire[3:0] d_2;
    wire[3:0] d_3;
    wire[3:0] d_4;
    wire[3:0] d_5;
    wire[3:0] d_6;
    wire[3:0] d_7;

    and14 d0(d_0, o[0], d[0]);
    and14 d1(d_1, o[1], d[1]);
    and14 d2(d_2, o[2], d[2]);
    and14 d3(d_3, o[3], d[3]);
    and14 d4(d_4, o[4], d[4]);
    and14 d5(d_5, o[5], d[5]);
    and14 d6(d_6, o[6], d[6]);
    and14 d7(d_7, o[7], d[7]);

    wire[3:0] tmp_data;

    or4 or_4(tmp_data, d_0, d_1, d_2, d_3, d_4, d_5, d_6, d_7);

    and14 and_14(o_data, c3, tmp_data);
endmodule

ARCHVM/Working with schemas/stack_structural_lite_tb.sv
`include "stack_structural.sv"

`define NOP 2'b00
`define PUSH 2'b01 
`define POP 2'b10
`define GET 2'b11

module stack_structural_tb;
    reg[3:0] I_DATA; wire[3:0] O_DATA;
    reg RESET, CLK;
    reg[1:0] COMMAND; 
    reg[2:0] INDEX;
    integer i, k, fd, TIMES; string OUTCSV;

    stack_structural_lite _stack(.O_DATA(O_DATA), .RESET(RESET), .CLK(CLK), .COMMAND(COMMAND), .INDEX(INDEX), .I_DATA(I_DATA));

    initial begin
        $dumpfile("dump.vcd"); $dumpvars(1, stack_structural_tb);
        if (!$value$plusargs("TIMES=%d", TIMES))
            TIMES = 5;
        if (!$value$plusargs("OUTCSV=%s", OUTCSV))
            OUTCSV = "st_stack_b.csv";
        $display("tb -> %s", OUTCSV);
            $display("TIMES -> %d", TIMES);
        $display("T\tO_DATA\tRESET\tCLK\tCOMMAND\tINDEX\tI_DATA");
        $monitor("%2d\t%5b\t%3b\t%6b\t%4b\t%4b\t%5b", $time, O_DATA, RESET, CLK, COMMAND, INDEX, I_DATA); 
        fd = $fopen(OUTCSV, "w");
        $fdisplay(fd, "T\tO_DATA\tRESET\tCLK\tCOMMAND\tINDEX\tI_DATA");
        k = (TIMES < 8) ? 8 : TIMES;
    end

    always #1 CLK = ~CLK;
    
    initial begin    
        CLK = 0; COMMAND = `NOP; RESET = 1; INDEX = 0; 
        #2 RESET = 0;
        for (i = 0; i < TIMES; i+=1) begin
            #2; COMMAND = `PUSH; #0.01 I_DATA = i+1;
        end
        #2 COMMAND = `NOP;
        #2 I_DATA = 4'b?;
        for (i = 0; i < k; i+=1) begin
            #2; COMMAND = `GET; INDEX = i;
        end
        #2 I_DATA = 4'b?; COMMAND = `NOP;
        for (i = 0; i < TIMES; i+=1) begin
            #2; COMMAND = `POP;       
            #2; COMMAND = `GET; INDEX = i;              
        end
        #2; COMMAND = `NOP; RESET = 1;             
        #2; RESET = 0;  
        #2 I_DATA = 4'b?; COMMAND = `NOP;
        for (i = 0; i < TIMES; i+=1) begin
            #2; COMMAND = `POP;                             
        end
        
        $fclose(fd);
        $finish;
    end

    always @(CLK) begin
        $fstrobe(fd, "%d\t%b\t%b\t%b\t%b\t%b\t%b", $time, O_DATA, RESET, CLK, COMMAND, INDEX, I_DATA);
    end

endmodule

ARCHVM/labwork2/dump.vcd
$date
	Wed Mar 27 15:03:43 2024
$end
$version
	Icarus Verilog
$end
$timescale
	1s
$end
$scope module stack_structural_tb $end
$var wire 4 ! O_DATA [3:0] $end
$var reg 1 " CLK $end
$var reg 2 # COMMAND [1:0] $end
$var reg 3 $ INDEX [2:0] $end
$var reg 4 % I_DATA [3:0] $end
$var reg 1 & RESET $end
$var integer 32 ' TIMES [31:0] $end
$var integer 32 ( fd [31:0] $end
$var integer 32 ) i [31:0] $end
$var integer 32 * k [31:0] $end
$upscope $end
$enddefinitions $end
$comment Show the parameter values. $end
$dumpall
$end
#0
$dumpvars
b1000 *
bx )
b10000000000000000000000000000011 (
b101 '
1&
bx %
b0 $
b0 #
0"
b0 !
$end
#1
1"
#2
0"
b0 )
0&
#3
1"
#4
b1 )
b1 %
0"
b1 #
#5
1"
#6
b10 )
b10 %
0"
#7
1"
#8
b11 )
b11 %
0"
#9
1"
#10
b100 )
b100 %
0"
#11
1"
#12
b101 )
b101 %
0"
#13
1"
#14
0"
b0 #
#15
1"
#16
0"
b0 )
bz %
#17
1"
#18
0"
b1 )
b11 #
#19
b101 !
1"
#20
b0 !
0"
b10 )
b1 $
#21
b100 !
1"
#22
b0 !
0"
b11 )
b10 $
#23
b11 !
1"
#24
b0 !
0"
b100 )
b11 $
#25
b10 !
1"
#26
b0 !
0"
b101 )
b100 $
#27
b1 !
1"
#28
b0 !
0"
b110 )
b101 $
#29
1"
#30
0"
b111 )
b110 $
#31
1"
#32
0"
b1000 )
b111 $
#33
1"
#34
0"
b0 )
b0 #
#35
1"
#36
0"
b10 #
#37
b101 !
1"
#38
b0 !
0"
b1 )
b0 $
b11 #
#39
b100 !
1"
#40
b0 !
0"
b10 #
#41
b100 !
1"
#42
b0 !
0"
b10 )
b1 $
b11 #
#43
b10 !
1"
#44
b0 !
0"
b10 #
#45
b11 !
1"
#46
b0 !
0"
b11 )
b10 $
b11 #
#47
1"
#48
0"
b10 #
#49
b10 !
1"
#50
b0 !
0"
b100 )
b11 $
b11 #
#51
1"
#52
0"
b10 #
#53
b1 !
1"
#54
b0 !
0"
b101 )
b100 $
b11 #
#55
b100 !
1"
#56
b0 !
0"
1&
b0 #
#57
1"
#58
0"
0&
#59
1"
#60
0"
b0 )
#61
1"
#62
0"
b1 )
b10 #
#63
1"
#64
0"
b10 )
#65
1"
#66
0"
b11 )
#67
1"
#68
0"
b100 )
#69
1"
#70
0"
b101 )
